<annotation>
	<folder>train_set</folder>
	<filename>frame_b5_3165.jpg</filename>
	<path>C:\Users\User\Desktop\train_set\frame_b5_3165.jpg</path>
	<source>
		<database>Unknown</database>
	</source>
	<size>
		<width>720</width>
		<height>1280</height>
		<depth>3</depth>
	</size>
	<segmented>0</segmented>
	<object>
		<name>not_app</name>
		<pose>Unspecified</pose>
		<truncated>0</truncated>
		<difficult>0</difficult>
		<bndbox>
			<xmin>20</xmin>
			<ymin>505</ymin>
			<xmax>581</xmax>
			<ymax>610</ymax>
		</bndbox>
	</object>
	<object>
		<name>not_app</name>
		<pose>Unspecified</pose>
		<truncated>0</truncated>
		<difficult>0</difficult>
		<bndbox>
			<xmin>18</xmin>
			<ymin>613</ymin>
			<xmax>490</xmax>
			<ymax>716</ymax>
		</bndbox>
	</object>
	<object>
		<name>not_app</name>
		<pose>Unspecified</pose>
		<truncated>0</truncated>
		<difficult>0</difficult>
		<bndbox>
			<xmin>20</xmin>
			<ymin>717</ymin>
			<xmax>507</xmax>
			<ymax>814</ymax>
		</bndbox>
	</object>
	<object>
		<name>not_app</name>
		<pose>Unspecified</pose>
		<truncated>0</truncated>
		<difficult>0</difficult>
		<bndbox>
			<xmin>23</xmin>
			<ymin>816</ymin>
			<xmax>373</xmax>
			<ymax>922</ymax>
		</bndbox>
	</object>
	<object>
		<name>not_app</name>
		<pose>Unspecified</pose>
		<truncated>0</truncated>
		<difficult>0</difficult>
		<bndbox>
			<xmin>20</xmin>
			<ymin>925</ymin>
			<xmax>356</xmax>
			<ymax>1024</ymax>
		</bndbox>
	</object>
	<object>
		<name>not_app</name>
		<pose>Unspecified</pose>
		<truncated>0</truncated>
		<difficult>0</difficult>
		<bndbox>
			<xmin>20</xmin>
			<ymin>1025</ymin>
			<xmax>329</xmax>
			<ymax>1127</ymax>
		</bndbox>
	</object>
	<object>
		<name>not_app</name>
		<pose>Unspecified</pose>
		<truncated>0</truncated>
		<difficult>0</difficult>
		<bndbox>
			<xmin>21</xmin>
			<ymin>1133</ymin>
			<xmax>348</xmax>
			<ymax>1227</ymax>
		</bndbox>
	</object>
	<object>
		<name>week</name>
		<pose>Unspecified</pose>
		<truncated>0</truncated>
		<difficult>0</difficult>
		<bndbox>
			<xmin>268</xmin>
			<ymin>152</ymin>
			<xmax>442</xmax>
			<ymax>205</ymax>
		</bndbox>
	</object>
</annotation>
