<annotation>
	<folder>pape_apps</folder>
	<filename>a_fielder631.jpg</filename>
	<path>C:\Users\Vilenskij Ser\Desktop\pape_apps\a_fielder631.jpg</path>
	<source>
		<database>Unknown</database>
	</source>
	<size>
		<width>696</width>
		<height>86</height>
		<depth>3</depth>
	</size>
	<segmented>0</segmented>
	<object>
		<name>name</name>
		<pose>Unspecified</pose>
		<truncated>1</truncated>
		<difficult>0</difficult>
		<bndbox>
			<xmin>98</xmin>
			<ymin>1</ymin>
			<xmax>264</xmax>
			<ymax>41</ymax>
		</bndbox>
	</object>
	<object>
		<name>time</name>
		<pose>Unspecified</pose>
		<truncated>0</truncated>
		<difficult>0</difficult>
		<bndbox>
			<xmin>102</xmin>
			<ymin>48</ymin>
			<xmax>150</xmax>
			<ymax>84</ymax>
		</bndbox>
	</object>
</annotation>
